Workbook

Sheet Painel Executivo
A1: HELP PEÇAS — PAINEL EXECUTIVO
A2: Atualizado em: Março 2026 · Meta: Liderança de Mercado até 2028
A4: FATURAMENTO MENSAL | D4: TICKET MÉDIO | F4: TAXA CONVERSÃO | H4: CAC | J4: NPS
A5: =Dados!O2 -> 1370000 | D5: =Dados!O5 -> 1.1768429 | F5: =Dados!O7 -> 5.6376901 | H5: =Dados!O8 -> 55 | J5: =Dados!O12 -> 60
A7: RECEITA vs META — Estamos no caminho certo?
A8: [Gráfico: Receita vs Meta por Mês]
A24: COMO ESTAMOS ALOCANDO O INVESTIMENTO EM MARKETING?
A25: [Gráfico: Investimento em Marketing por Canal]
A40: EVOLUÇÃO DO FUNIL DE CONVERSÃO
A41: [Gráfico: Funil de Conversão (Visitantes → Leads → Carrinhos → Pedidos)]

Sheet Dados
A1: Métrica | B1: Jan | C1: Fev | D1: Mar | E1: Abr | F1: Mai | G1: Jun | H1: Jul | I1: Ago | J1: Set | K1: Out | L1: Nov | M1: Dez | N1: Meta Anual | O1: Acum. YTD | P1: % Meta
A2: Faturamento Bruto (R$) | B2: 420000 | C2: 465000 | D2: 485000 | N2: 6000000 | O2: =SUMIF(B2:M2,">0") -> 1370000 | P2: =IF(N2=0, 0, O2/N2) -> 0.22833333
A3: Receita Líquida (R$) | B3: 357000 | C3: 395000 | D3: 412000 | N3: 5100000 | O3: =SUMIF(B3:M3,">0") -> 1164000 | P3: =IF(N3=0, 0, O3/N3) -> 0.22823529
A4: Pedidos | B4: 1750 | C4: 1920 | D4: 2003 | N4: 25000 | O4: =SUMIF(B4:M4,">0") -> 5673 | P4: =IF(N4=0, 0, O4/N4) -> 0.22692
A5: Ticket Médio (R$) | B5: =IF(B3=0, 0, B2/B3) -> 1.1764706 | C5: =IF(C3=0, 0, C2/C3) -> 1.1772152 | N5: 240 | O5: =AVERAGEIF(B5:M5,">0") -> 1.1768429 | P5: =IF(N5=0, 0, O5/N5) -> 0.004903512
A6: Visitantes Únicos | B6: 62500 | C6: 71000 | D6: 78500 | N6: 900000 | O6: =SUMIF(B6:M6,">0") -> 212000 | P6: =IF(N6=0, 0, O6/N6) -> 0.23555556
A7: Taxa de Conversão (%) | B7: =IF(B6=0, 0, B3/B6) -> 5.712 | C7: =IF(C6=0, 0, C3/C6) -> 5.5633803 | N7: 0.028 | O7: =AVERAGEIF(B7:M7,">0") -> 5.6376901 | P7: =IF(N7=0, 0, O7/N7) -> 201.34608
A8: CAC (R$) | B8: 58 | C8: 55 | D8: 52 | N8: 50 | O8: =AVERAGEIF(B8:M8,">0") -> 55 | P8: =IF(N8=0, 0, O8/N8) -> 1.1
A9: LTV (R$) | B9: 580 | C9: 610 | D9: 640 | N9: 720 | O9: =AVERAGEIF(B9:M9,">0") -> 610 | P9: =IF(N9=0, 0, O9/N9) -> 0.84722222
A10: LTV/CAC | B10: =IF(B8=0, 0, B9/B8) -> 10 | C10: =IF(C8=0, 0, C9/C8) -> 11.090909 | N10: 14.4 | O10: =AVERAGEIF(B10:M10,">0") -> 10.545455 | P10: =IF(N10=0, 0, O10/N10) -> 0.73232323
A11: ROAS | B11: 3.8 | C11: 4.1 | D11: 4.5 | N11: 5 | O11: =AVERAGEIF(B11:M11,">0") -> 4.1333333 | P11: =IF(N11=0, 0, O11/N11) -> 0.82666667
A12: NPS | B12: 58 | C12: 60 | D12: 62 | N12: 70 | O12: =AVERAGEIF(B12:M12,">0") -> 60 | P12: =IF(N12=0, 0, O12/N12) -> 0.85714286
A13: Margem Bruta (%) | B13: 0.36 | C13: 0.37 | D13: 0.38 | N13: 0.4 | O13: =AVERAGEIF(B13:M13,">0") -> 0.37 | P13: =IF(N13=0, 0, O13/N13) -> 0.925
A14: Giro Estoque (dias) | B14: 28 | C14: 26 | D14: 24 | N14: 20 | O14: =AVERAGEIF(B14:M14,">0") -> 26 | P14: =IF(N14=0, 0, O14/N14) -> 1.3
A15: SLA Entrega (%) | B15: 0.92 | C15: 0.94 | D15: 0.95 | N15: 0.97 | O15: =AVERAGEIF(B15:M15,">0") -> 0.93666667 | P15: =IF(N15=0, 0, O15/N15) -> 0.96563574
A16: CSAT | B16: 4.2 | C16: 4.3 | D16: 4.4 | N16: 4.7 | O16: =AVERAGEIF(B16:M16,">0") -> 4.3 | P16: =IF(N16=0, 0, O16/N16) -> 0.91489362
A17: SKUs Ativos | B17: 1200 | C17: 1450 | D17: 1680 | N17: 3000 | O17: =SUMIF(B17:M17,">0") -> 4330 | P17: =IF(N17=0, 0, O17/N17) -> 1.4433333
A18: Taxa Devolução (%) | B18: 0.038 | C18: 0.032 | D18: 0.028 | N18: 0.025 | O18: =AVERAGEIF(B18:M18,">0") -> 0.032666667 | P18: =IF(N18=0, 0, O18/N18) -> 1.3066667
A19: Leads Gerados | B19: 3200 | C19: 3800 | D19: 4100 | N19: 50000 | O19: =SUMIF(B19:M19,">0") -> 11100 | P19: =IF(N19=0, 0, O19/N19) -> 0.222
A20: Carrinhos Criados | B20: 4800 | C20: 5400 | D20: 5900 | N20: 65000 | O20: =SUMIF(B20:M20,">0") -> 16100 | P20: =IF(N20=0, 0, O20/N20) -> 0.24769231
A21: Clientes Recorrentes (%) | B21: 0.12 | C21: 0.14 | D21: 0.16 | N21: 0.25 | O21: =AVERAGEIF(B21:M21,">0") -> 0.14 | P21: =IF(N21=0, 0, O21/N21) -> 0.56

Sheet Marketing
A1: ANÁLISE DE CANAIS DE MARKETING
A3: Canal | B3: Investimento Mensal (R$) | C3: Receita Gerada (R$) | D3: ROAS | E3: Leads | F3: CPL (R$) | G3: Conversões | H3: CPA (R$) | I3: % Orçamento
A4: Meta Ads | B4: 4500 | C4: 18000 | D4: =C4/B4 -> 4 | E4: 1200 | F4: =B4/E4 -> 3.75 | G4: 420 | H4: =B4/G4 -> 10.714286 | I4: =B4/SUM($B$4:$B$11) -> 0.32142857
A5: Google Ads | B5: 3500 | C5: 21000 | D5: =C5/B5 -> 6 | E5: 900 | F5: =B5/E5 -> 3.8888889 | G5: 380 | H5: =B5/G5 -> 9.2105263 | I5: =B5/SUM($B$4:$B$11) -> 0.25
A6: TikTok Ads | B6: 1500 | C6: 4500 | D6: =C6/B6 -> 3 | E6: 600 | F6: =B6/E6 -> 2.5 | G6: 90 | H6: =B6/G6 -> 16.666667 | I6: =B6/SUM($B$4:$B$11) -> 0.10714286
A7: Influenciadores | B7: 2000 | C7: 8000 | D7: =C7/B7 -> 4 | E7: 800 | F7: =B7/E7 -> 2.5 | G7: 160 | H7: =B7/G7 -> 12.5 | I7: =B7/SUM($B$4:$B$11) -> 0.14285714
A8: Conteúdo Orgânico | B8: 1000 | C8: 6000 | D8: =C8/B8 -> 6 | E8: 500 | F8: =B8/E8 -> 2 | G8: 200 | H8: =B8/G8 -> 5 | I8: =B8/SUM($B$4:$B$11) -> 0.071428571
A9: Podcast "Rolê Infinito" | B9: 800 | C9: 2400 | D9: =C9/B9 -> 3 | E9: 300 | F9: =B9/E9 -> 2.6666667 | G9: 60 | H9: =B9/G9 -> 13.333333 | I9: =B9/SUM($B$4:$B$11) -> 0.057142857
A10: Email Marketing | B10: 300 | C10: 3600 | D10: =C10/B10 -> 12 | E10: 200 | F10: =B10/E10 -> 1.5 | G10: 180 | H10: =B10/G10 -> 1.6666667 | I10: =B10/SUM($B$4:$B$11) -> 0.021428571
A11: WhatsApp | B11: 400 | C11: 4800 | D11: =C11/B11 -> 12 | E11: 350 | F11: =B11/E11 -> 1.1428571 | G11: 240 | H11: =B11/G11 -> 1.6666667 | I11: =B11/SUM($B$4:$B$11) -> 0.028571429
A12: TOTAL | B12: =SUM(B4:B11) -> 14000 | C12: =SUM(C4:C11) -> 68300 | E12: =SUM(E4:E11) -> 4850 | G12: =SUM(G4:G11) -> 1730

Sheet Projetos
A1: ID | B1: Área | C1: Projeto/Entregável | D1: Responsável | E1: Data Início | F1: Data Prazo | G1: Status | H1: Prioridade | I1: % Conclusão | J1: Semáforo | K1: Mar 26 | L1: Apr 26 | M1: May 26 | N1: Jun 26 | O1: Jul 26 | P1: Aug 26 | Q1: Sep 26 | R1: Oct 26 | S1: Nov 26 | T1: Dec 26 | U1: Jan 27 | V1: Feb 27
A2: 1 | B2: E-commerce | C2: Migração plataforma VTEX | D2: Rafael | E2: 46023 | F2: 46112 | G2: Em Andamento | H2: Crítica | I2: 0.75 | J2: ● | K2: █
A3: 2 | B3: E-commerce | C3: Integração Mercado Livre | D3: Tech | E3: 46068 | F3: 46142 | G3: Em Andamento | H3: Alta | I3: 0.4 | J3: ● | K3: █ | L3: █
A4: 3 | B4: E-commerce | C4: Integração Amazon BR | D4: Tech | E4: 46113 | F4: 46203 | G4: Pendente | H4: Alta | I4: 0 | J4: ● | L4: █ | M4: █ | N4: █
A5: 4 | B5: E-commerce | C5: Cadastro 2000 SKUs | D5: Ops | E5: 46023 | F5: 46203 | G5: Em Andamento | H5: Crítica | I5: 0.56 | J5: ● | K5: █ | L5: █ | M5: █ | N5: █
A6: 5 | B6: E-commerce | C6: App mobile (design) | D6: Tech | E6: 46143 | F6: 46265 | G6: Pendente | H6: Média | I6: 0 | J6: ● | M6: █ | N6: █ | O6: █ | P6: █
A7: 6 | B7: E-commerce | C7: Programa de fidelidade | D7: Mkt | E7: 46174 | F7: 46295 | G7: Pendente | H7: Média | I7: 0 | J7: ● | N7: █ | O7: █ | P7: █ | Q7: █
A8: 7 | B8: E-commerce | C8: Private label "Help Original" | D8: Produto | E8: 46204 | F8: 46387 | G8: Pendente | H8: Alta | I8: 0 | J8: ● | O8: █ | P8: █ | Q8: █ | R8: █ | S8: █ | T8: █
A9: 8 | B9: Marketing | C9: Campanha lançamento Q1 | D9: Mkt | E9: 46023 | F9: 46112 | G9: Concluído | H9: Crítica | I9: 1 | J9: ● | K9: █
A10: 9 | B10: Marketing | C10: Setup Google Ads Shopping | D10: Mkt | E10: 46054 | F10: 46081 | G10: Concluído | H10: Alta | I10: 1 | J10: ●
A11: 10 | B11: Marketing | C11: Podcast "Rolê Infinito" S1 | D11: Conteúdo | E11: 46023 | F11: 46203 | G11: Em Andamento | H11: Alta | I11: 0.33 | J11: ● | K11: █ | L11: █ | M11: █ | N11: █
A12: 11 | B12: Marketing | C12: Editorial "Vozes da Cidade" | D12: Conteúdo | E12: 46082 | F12: 46265 | G12: Em Andamento | H12: Média | I12: 0.1 | J12: ● | K12: █ | L12: █ | M12: █ | N12: █ | O12: █ | P12: █
A13: 12 | B13: Marketing | C13: Parcerias 10 influenciadores | D13: Mkt | E13: 46054 | F13: 46173 | G13: Em Andamento | H13: Alta | I13: 0.3 | J13: ● | K13: █ | L13: █ | M13: █
A14: 13 | B14: Marketing | C14: SEO — 50 artigos blog | D14: Conteúdo | E14: 46023 | F14: 46203 | G14: Em Andamento | H14: Média | I14: 0.24 | J14: ● | K14: █ | L14: █ | M14: █ | N14: █
A15: 14 | B15: Marketing | C15: TikTok channel launch | D15: Mkt | E15: 46082 | F15: 46142 | G15: Em Andamento | H15: Média | I15: 0.2 | J15: ● | K15: █ | L15: █
A16: 15 | B16: Marketing | C16: Brand awareness survey | D16: Mkt | E16: 46174 | F16: 46203 | G16: Pendente | H16: Média | I16: 0 | J16: ● | N16: █
A17: 16 | B17: Operações | C17: Contrato 5 fornecedores cert. | D17: Ops | E17: 46023 | F17: 46142 | G17: Em Andamento | H17: Crítica | I17: 0.6 | J17: ● | K17: █ | L17: █
A18: 17 | B18: Operações | C18: Setup WMS Bling | D18: Ops | E18: 46054 | F18: 46112 | G18: Em Andamento | H18: Alta | I18: 0.8 | J18: ● | K18: █
A19: 18 | B19: Operações | C19: Centro distribuição SP | D19: Ops | E19: 46113 | F19: 46234 | G19: Pendente | H19: Alta | I19: 0 | J19: ● | L19: █ | M19: █ | N19: █ | O19: █
A20: 19 | B20: Operações | C20: Processo fulfillment D+1 | D20: Ops | E20: 46082 | F20: 46173 | G20: Em Andamento | H20: Crítica | I20: 0.25 | J20: ● | K20: █ | L20: █ | M20: █
A21: 20 | B21: Operações | C21: Qualidade fornecedores | D21: Ops | E21: 46143 | F21: 46265 | G21: Pendente | H21: Média | I21: 0 | J21: ● | M21: █ | N21: █ | O21: █ | P21: █
A22: 21 | B22: Operações | C22: Contrato Melhor Envio/Kangu | D22: Ops | E22: 46023 | F22: 46081 | G22: Concluído | H22: Alta | I22: 1 | J22: ●
A23: 22 | B23: People | C23: Contratar Head de Marketing | D23: RH | E23: 46082 | F23: 46142 | G23: Em Andamento | H23: Crítica | I23: 0.5 | J23: ● | K23: █ | L23: █
A24: 23 | B24: People | C24: Contratar Head de Operações | D24: RH | E24: 46113 | F24: 46173 | G24: Pendente | H24: Crítica | I24: 0 | J24: ● | L24: █ | M24: █
A25: 24 | B25: People | C25: Contratar Analista de Dados | D25: RH | E25: 46143 | F25: 46203 | G25: Pendente | H25: Alta | I25: 0 | J25: ● | M25: █ | N25: █
A26: 25 | B26: Tech | C26: Setup GA4 + dashboards | D26: Tech | E26: 46023 | F26: 46081 | G26: Concluído | H26: Alta | I26: 1 | J26: ●
A27: 26 | B27: Tech | C27: Integração CRM HubSpot | D27: Tech | E27: 46054 | F27: 46142 | G27: Em Andamento | H27: Alta | I27: 0.45 | J27: ● | K27: █ | L27: █
A28: 27 | B28: Tech | C28: Chatbot WhatsApp API | D28: Tech | E28: 46082 | F28: 46173 | G28: Em Andamento | H28: Média | I28: 0.15 | J28: ● | K28: █ | L28: █ | M28: █
A29: 28 | B29: Tech | C29: Setup Zendesk CS | D29: Tech | E29: 46082 | F29: 46142 | G29: Em Andamento | H29: Alta | I29: 0.3 | J29: ● | K29: █ | L29: █
A30: 29 | B30: CS | C30: Base conhecimento FAQ | D30: CS | E30: 46113 | F30: 46173 | G30: Pendente | H30: Média | I30: 0 | J30: ● | L30: █ | M30: █
A31: 30 | B31: CS | C31: Treinamento equipe SAC | D31: CS | E31: 46143 | F31: 46203 | G31: Pendente | H31: Alta | I31: 0 | J31: ● | M31: █ | N31: █

Sheet Roadmap 2026-2028
A1: Pilar Estratégico | B1: Iniciativa | C1: 2026 Q1 | D1: 2026 Q2 | E1: 2026 Q3 | F1: 2026 Q4 | G1: 2027 Q1 | H1: 2027 Q2 | I1: 2027 Q3 | J1: 2027 Q4 | K1: 2028 Q1 | L1: 2028 Q2 | M1: 2028 Q3 | N1: 2028 Q4
A2: E-commerce | B2: Migração VTEX | C2: █
B3: Marketplaces (ML, Amazon) | D3: █ | E3: █
B4: App mobile | E4: █ | F4: █
B5: Fidelidade | E5: █ | F5: █ | G5: █
A6: Marketing & Conteúdo | B6: Podcast "Rolê Infinito" | C6: █ | D6: █ | E6: █
B7: Blog & SEO 50 artigos | C7: █ | D7: █ | E7: █
B8: Influenciadores | D8: █ | E8: █ | F8: █ | G8: █
B9: Editorial lifestyle | E9: █ | F9: █ | G9: █ | H9: █
A10: Operações | B10: Fornecedores certificados | C10: █ | D10: █
B11: WMS Bling | C11: █
B12: Centro distribuição SP | D12: █ | E12: █
B13: Fulfillment D+1 | D13: █ | E13: █ | F13: █
A14: Tecnologia | B14: GA4 + Dashboards | C14: █
B15: HubSpot CRM | D15: █ | E15: █
B16: Chatbot WhatsApp | D16: █ | E16: █
B17: Zendesk CS | D17: █ | E17: █
A18: Pessoas | B18: Head de Marketing | D18: █ | E18: █ | F18: █ | G18: █
B19: Head de Operações | D19: █ | E19: █ | F19: █ | G19: █
B20: Time de dados | E20: █ | F20: █ | G20: █ | H20: █
A21: Produto | B21: Private label "Help Original" | E21: █ | F21: █
B22: 2000+ SKUs | C22: █ | D22: █ | E22: █
A23: Financeiro | B23: Rentabilidade positiva | F23: █ | G23: █ | H23: █ | I23: █ | J23: █ | K23: █ | L23: █ | M23: █ | N23: █
B24: Série A/Financiamento | E24: █ | F24: █

Sheet Equipe & Custos
A1: Fase | B1: Cargo | C1: Departamento | D1: Tipo | E1: Salário/Mês (R$) | F1: Encargos (70%) | G1: Custo Total/Mês | H1: Contratação | I1: Status
A2: Fase 1 (2026) | B2: CEO/Founder | C2: Exec | D2: PJ | E2: 15000 | F2: =IF(D2="CLT", E2*0.7, 0) -> 0 | G2: =E2+F2 -> 15000 | H2: 01/01/26 | I2: Ativo
B3: Dev Fullstack | C3: Tech | D3: CLT | E3: 8000 | F3: =IF(D3="CLT", E3*0.7, 0) -> 5600 | G3: =E3+F3 -> 13600 | H3: 01/01/26 | I3: Ativo
B4: Analista E-commerce | C4: Mkt | D4: CLT | E4: 4500 | F4: =IF(D4="CLT", E4*0.7, 0) -> 3150 | G4: =E4+F4 -> 7650 | H4: 01/01/26 | I4: Ativo
B5: Social Media | C5: Mkt | D5: CLT | E5: 3500 | F5: =IF(D5="CLT", E5*0.7, 0) -> 2450 | G5: =E5+F5 -> 5950 | H5: 01/01/26 | I5: Ativo
B6: Designer | C6: Design | D6: PJ | E6: 4000 | F6: =IF(D6="CLT", E6*0.7, 0) -> 0 | G6: =E6+F6 -> 4000 | H6: 01/01/26 | I6: Ativo
B7: Operador Estoque | C7: Ops | D7: CLT | E7: 2500 | F7: =IF(D7="CLT", E7*0.7, 0) -> 1750 | G7: =E7+F7 -> 4250 | H7: 01/01/26 | I7: Ativo
B8: Atendente SAC | C8: CS | D8: CLT | E8: 2800 | F8: =IF(D8="CLT", E8*0.7, 0) -> 1960 | G8: =E8+F8 -> 4760 | H8: 01/02/26 | I8: Ativo
A9: Fase 2 (2027) | B9: Head Marketing | C9: Mkt | D9: CLT | E9: 12000 | F9: =IF(D9="CLT", E9*0.7, 0) -> 8400 | G9: =E9+F9 -> 20400 | H9: 01/04/26 | I9: Recrutando
B10: Head Operações | C10: Ops | D10: CLT | E10: 12000 | F10: =IF(D10="CLT", E10*0.7, 0) -> 8400 | G10: =E10+F10 -> 20400 | H10: 01/05/26 | I10: Recrutando
B11: Videomaker | C11: Conteúdo | D11: PJ | E11: 4500 | F11: =IF(D11="CLT", E11*0.7, 0) -> 0 | G11: =E11+F11 -> 4500 | H11: 01/03/26 | I11: Ativo
B12: Redator | C12: Conteúdo | D12: CLT | E12: 3500 | F12: =IF(D12="CLT", E12*0.7, 0) -> 2450 | G12: =E12+F12 -> 5950 | H12: 01/02/26 | I12: Ativo
B13: Community Manager | C13: Mkt | D13: CLT | E13: 3000 | F13: =IF(D13="CLT", E13*0.7, 0) -> 2100 | G13: =E13+F13 -> 5100 | H13: 01/05/26 | I13: Pendente
B14: CS Especialista | C14: CS | D14: CLT | E14: 4000 | F14: =IF(D14="CLT", E14*0.7, 0) -> 2800 | G14: =E14+F14 -> 6800 | H14: 01/04/26 | I14: Pendente
B15: CS Técnico | C15: CS | D15: CLT | E15: 5000 | F15: =IF(D15="CLT", E15*0.7, 0) -> 3500 | G15: =E15+F15 -> 8500 | H15: 01/06/26 | I15: Pendente
B16: Analista de Dados | C16: Tech | D16: CLT | E16: 7000 | F16: =IF(D16="CLT", E16*0.7, 0) -> 4900 | G16: =E16+F16 -> 11900 | H16: 01/05/26 | I16: Recrutando
B17: Compras/Supply Chain | C17: Ops | D17: CLT | E17: 6000 | F17: =IF(D17="CLT", E17*0.7, 0) -> 4200 | G17: =E17+F17 -> 10200 | H17: 01/06/26 | I17: Pendente
A19: TOTAL FASE 1 | G19: =SUM(G2:G8) -> 55210
A20: TOTAL FASE 2 | G20: =SUM(G9:G17) -> 93750
